guruji/__init__.py
guruji/hello.py
guruji-0.1.dist-info/METADATA
guruji-0.1.dist-info/WHEEL
guruji-0.1.dist-info/top_level.txt
guruji-0.1.dist-info/RECORD
