Metadata-Version: 2.1
Name: guruji
Version: 0.1
Summary: Hardcore library
Author: danishk sinha
Author-email: thisisdanishk@gmail.com
